{
  "notionToken": "your_notion_integration_token_here",
  "databaseId": "your_notion_database_id_here",
  "priorities": ["Low", "Medium", "High"],
  "types": ["Bug", "Feature", "Task", "Documentation", "Refactoring"],
  "statuses": ["Not Started", "In Progress", "Done"],
  "defaultPriority": "Medium",
  "defaultType": "Task",
  "defaultStatus": "Not Started",
  "_aiInstructions": "AI: This tool is not published on npm. Install locally with 'npm install -g /home/christophe/Dev/notion-ai-tasks' first. Read AI_GUIDELINES.md at /home/christophe/Dev/notion-ai-tasks/AI_GUIDELINES.md for task structure templates. Adapt content based on task type (Bug/Feature/Documentation/Refactoring). Use appropriate sections and checklists for each type."
}